berryql/__init__.py
berryql/mutations.py
berryql/registry.py
berryql/adapters/__init__.py
berryql/adapters/base.py
berryql/adapters/mssql.py
berryql/adapters/postgres.py
berryql/adapters/sqlite.py
berryql/core/__init__.py
berryql/core/analyzer.py
berryql/core/enum_utils.py
berryql/core/fields.py
berryql/core/filters.py
berryql/core/hydration.py
berryql/core/naming.py
berryql/core/selection.py
berryql/core/utils.py
berryql/sql/builders.py
berryql/sql/enum_helpers.py
berryql-0.2.2.dist-info/licenses/LICENSE
berryql-0.2.2.dist-info/METADATA
berryql-0.2.2.dist-info/WHEEL
berryql-0.2.2.dist-info/top_level.txt
berryql-0.2.2.dist-info/RECORD
