Metadata-Version: 2.4
Name: berryql
Version: 0.2.2
Summary: A powerful GraphQL query optimization library for Strawberry GraphQL and SQLAlchemy
Author: Yurii Tolkunov, Claude Sonnet 4, GPT-5, GPT-5.1-Codex, BerryQL Contributors
License-Expression: MIT
Project-URL: Homepage, https://github.com/uratol/berryql
Project-URL: Repository, https://github.com/uratol/berryql
Project-URL: Documentation, https://github.com/uratol/berryql#readme
Project-URL: Bug Tracker, https://github.com/uratol/berryql/issues
Keywords: graphql,strawberry,sqlalchemy,query-optimization,orm
Classifier: Development Status :: 4 - Beta
Classifier: Intended Audience :: Developers
Classifier: Programming Language :: Python :: 3
Classifier: Programming Language :: Python :: 3.8
Classifier: Programming Language :: Python :: 3.9
Classifier: Programming Language :: Python :: 3.10
Classifier: Programming Language :: Python :: 3.11
Classifier: Programming Language :: Python :: 3.12
Classifier: Programming Language :: Python :: 3.13
Classifier: Topic :: Software Development :: Libraries :: Python Modules
Classifier: Topic :: Database
Classifier: Topic :: Internet :: WWW/HTTP :: Dynamic Content
Classifier: Framework :: AsyncIO
Requires-Python: >=3.8
License-File: LICENSE
Requires-Dist: strawberry-graphql>=0.211.0
Requires-Dist: sqlalchemy>=2.0.25
Requires-Dist: graphql-core>=3.2.4
Requires-Dist: inflection>=0.5.1
Provides-Extra: dev
Requires-Dist: pytest>=8.2; extra == "dev"
Requires-Dist: pytest-asyncio>=0.23; extra == "dev"
Requires-Dist: pytest-cov>=5.0; extra == "dev"
Requires-Dist: black>=24.3; extra == "dev"
Requires-Dist: isort>=5.13; extra == "dev"
Requires-Dist: mypy>=1.10; extra == "dev"
Requires-Dist: flake8>=7.0; extra == "dev"
Requires-Dist: pre-commit>=3.7; extra == "dev"
Requires-Dist: build>=1.2.1; extra == "dev"
Requires-Dist: twine>=5.0.0; extra == "dev"
Requires-Dist: check-manifest>=0.50; extra == "dev"
Provides-Extra: test
Requires-Dist: pytest>=8.2; extra == "test"
Requires-Dist: pytest-asyncio>=0.23; extra == "test"
Requires-Dist: pytest-cov>=5.0; extra == "test"
Requires-Dist: aiosqlite>=0.19.0; extra == "test"
Provides-Extra: adapters
Requires-Dist: asyncpg>=0.29.0; extra == "adapters"
Requires-Dist: pyodbc>=5.2.0; extra == "adapters"
Requires-Dist: python-dotenv>=1.0.1; extra == "adapters"
Dynamic: license-file
